gingado/__init__.py
gingado/augmentation.py
gingado/benchmark.py
gingado/datasets.py
gingado/estimators.py
gingado/internals.py
gingado/model_documentation.py
gingado/settings.py
gingado/utils.py
gingado/data/GrowthData.mat
gingado/data/dataset_BarroLee_1994.csv
gingado/data/dataset_lr_monthly.csv
gingado/data/dataset_lr_weekly.csv
gingado/data/inflation_data.csv
gingado-0.2.7.dist-info/licenses/LICENSE
tests/__init__.py
tests/test_temporal.py
gingado-0.2.7.dist-info/METADATA
gingado-0.2.7.dist-info/WHEEL
gingado-0.2.7.dist-info/top_level.txt
gingado-0.2.7.dist-info/RECORD
