Metadata-Version: 2.4
Name: gingado
Version: 0.2.7
Summary: A machine learning library for economics and finance
Home-page: https://github.com/bis-med-it/gingado
Author: Douglas K. G. de Araujo
Author-email: Douglas.Araujo@bis.org
License: Apache-2.0
Classifier: Development Status :: 5 - Production/Stable
Classifier: Intended Audience :: Developers
Classifier: Natural Language :: English
Classifier: License :: OSI Approved :: Apache Software License
Classifier: Programming Language :: Python :: 3
Classifier: Programming Language :: Python :: 3.7
Classifier: Programming Language :: Python :: 3.8
Classifier: Programming Language :: Python :: 3.9
Classifier: Programming Language :: Python :: 3.10
Classifier: Programming Language :: Python :: 3.11
Classifier: Programming Language :: Python :: 3.12
Classifier: Programming Language :: Python :: 3.13
Requires-Python: >=3.7
License-File: LICENSE
Requires-Dist: numpy>=1.21
Requires-Dist: pandas>=1.3.5
Requires-Dist: sdmx1>=2.15.0
Requires-Dist: scikit-learn>=1.6.1
Requires-Dist: requests_cache>=0.9.1
Requires-Dist: matplotlib>=3.5
Requires-Dist: requests>=2.31.0
Requires-Dist: keras>=3.5.0
Provides-Extra: dev
Requires-Dist: tensorflow; extra == "dev"
Requires-Dist: torch; extra == "dev"
Requires-Dist: statsmodels; extra == "dev"
Requires-Dist: nbformat; extra == "dev"
Requires-Dist: nbclient; extra == "dev"
Requires-Dist: pandas-stubs; extra == "dev"
Requires-Dist: pre-commit; extra == "dev"
Requires-Dist: pytest; extra == "dev"
Requires-Dist: jupyter; extra == "dev"
Dynamic: author
Dynamic: author-email
Dynamic: classifier
Dynamic: description
Dynamic: description-content-type
Dynamic: home-page
Dynamic: license
Dynamic: license-file
Dynamic: provides-extra
Dynamic: requires-dist
Dynamic: requires-python
Dynamic: summary
